edw_catapult/__init__.py
edw_catapult/main.py
edw_catapult-0.0.2.dist-info/LICENSE
edw_catapult-0.0.2.dist-info/METADATA
edw_catapult-0.0.2.dist-info/WHEEL
edw_catapult-0.0.2.dist-info/top_level.txt
edw_catapult-0.0.2.dist-info/RECORD
