Metadata-Version: 2.1
Name: edw-catapult
Version: 0.0.2
Summary: A POC for EDW Catapult
Home-page: https://github.com/MassStreetAnalytics/edw_catapult
Author: Bob Wakefield
Author-email: bob@MassStreet.net
License: UNKNOWN
Project-URL: Bug Tracker, https://github.com/MassStreetAnalytics/edw_catapult/issues
Platform: UNKNOWN
Classifier: Programming Language :: Python :: 3
Classifier: License :: OSI Approved :: MIT License
Classifier: Operating System :: Microsoft :: Windows :: Windows 10
Requires-Python: >=3.6
License-File: LICENSE
